ontag/__init__.py
ontag/boolEval.py
ontag-1.1.1.dist-info/METADATA
ontag-1.1.1.dist-info/WHEEL
ontag-1.1.1.dist-info/top_level.txt
ontag-1.1.1.dist-info/RECORD
