Metadata-Version: 2.1
Name: ontag
Version: 1.1.1
Summary: Olimpic Number Theory and Algebra question Generator
Home-page: UNKNOWN
Author: Wojtek M
License: MIT
Platform: UNKNOWN
Classifier: Programming Language :: Python :: 3.9
